apifind/__init__.py
apifind/finder.py
api_finder-1.0.0.dist-info/METADATA
api_finder-1.0.0.dist-info/WHEEL
api_finder-1.0.0.dist-info/entry_points.txt
api_finder-1.0.0.dist-info/top_level.txt
api_finder-1.0.0.dist-info/RECORD
